setup.cfg
setup.py
prtgrestcli/__init__.py
prtgrestcli/enums.py
prtgrestcli/exceptions.py
prtgrestcli/models.py
pyprtgrestcli.egg-info/PKG-INFO
pyprtgrestcli.egg-info/SOURCES.txt
pyprtgrestcli.egg-info/dependency_links.txt
pyprtgrestcli.egg-info/top_level.txt