Metadata-Version: 1.1
Name: pyprtgrestcli
Version: 0.0.2
Summary: A Python implementation for PrtgHTTPPushDataAdvancedSensor
Home-page: https://github.com/zeent/pyprtgrestcli
Author: Joan Camps
Author-email: joan.camps@zeent.com
License: MIT
Keywords: PRTG,PrtgHTTPPushDataAdvancedSensor
Platform: UNKNOWN
Classifier: Development Status :: 2 - Pre-Alpha
Classifier: Environment :: Console
Classifier: Intended Audience :: Developers
Classifier: License :: OSI Approved :: MIT License
Classifier: Operating System :: OS Independent
Classifier: Programming Language :: Python
Classifier: Programming Language :: Python :: 2.6
Classifier: Programming Language :: Python :: 2.7
Classifier: Programming Language :: Python :: 3
Classifier: Programming Language :: Python :: 3.2
Classifier: Programming Language :: Python :: 3.3
Classifier: Programming Language :: Python :: 3.4
